Workbook

Sheet Инструкция
A1: Единая база угроз и рулетка типов проектов ИБ (2026 г.)
A3: Состав файла
A4: Лист «База_угроз_эталон» — 70 угроз по семи категориям, с экспертной отметкой актуальности по пяти типам объекта защиты (столбцы G-K) и с указанием профильного типа проекта ИБ (столбец L), который наиболее прямо связан с этой угрозой. База расширена по сравнению с версией из 47 угроз: добавлены угрозы, специфичные для программно-аппаратных проектов (МЭ/NGFW, DLP, IAM/MFA/SSO, SIEM/SOC, Backup/DR, СКЗИ) и организационно-административных проектов (политика ИБ, категорирование КИИ, 152-ФЗ, паспорт безопасности, аудит/пентест, обучение персонала). Лист рекомендуется скрыть или защитить паролем перед выдачей студентам — он является эталоном (ключом) для преподавателя.
A6: Лист «Бланк_студента» — выбор объекта защиты (B3), ручная простановка флажков по угрозам и автоматическая сверка с эталоном.
A8: Лист «Рулетка_проекта» — механика выбора типа проекта ИБ. Все 20 типов проектов сгруппированы в три «сундука»: I — инженерно-технические средства охраны (ИТСО), II — программно-аппаратный проект ИБ, III — организационно-административный проект. Выбор типа проекта — случайный (клавиша F9 пересчитывает лист, формула выбирает новый вариант) и НЕ фильтруется по ранее выбранному объекту защиты: комбинация может оказаться нереалистичной (например, «Частный дом» + «Категорирование КИИ»). Это сделано намеренно: если выпавшая комбинация не имеет смысла, студент обязан письменно обосновать, почему проект неприменим к данному заказчику, и предложить разумную замену. Такое задание тренирует именно то пограничное суждение, которое хуже всего поддаётся автоматизации ИИ — в отличие от прямой подстановки по заранее заданному фильтру.
A10: Как крутить рулетку без F9 (важно для клавиатуры Mac)
A11: Клавиша F9 на Mac по умолчанию отвечает за яркость экрана, поэтому вызывать пересчёт клавишей F9 неудобно. Формула рулетки использует функцию RANDBETWEEN, которая является «волатильной» и пересчитывается автоматически при ЛЮБОМ изменении в любой ячейке книги — не только по F9. На листе «Рулетка_проекта» рядом с результатом добавлена ячейка «Крутить»: кликните в неё, введите любое число и нажмите Enter — рулетка пересчитается сама. Кто предпочитает клавиатуру: на Mac это Fn+F9 (или Cmd+= в некоторых версиях Excel), на Windows — F9.
A13: Лист «Оценка_риска_Дельфи» — балльная оценка текущего риска объекта ДО внедрения проекта ИБ.
A14: Метод: Риск = Вероятность (P) x Тяжесть ущерба (I), P и I оцениваются по шкале 1-5 двумя экспертами (студент и приглашённый одногруппник) независимо друг от друга — раунд 1. При расхождении оценок на 2 балла и более лист помечает угрозу «обсудите (раунд 2)»: эксперты обсуждают и вписывают согласованные P и I вручную поверх формулы-подсказки (среднего). Это воспроизводит ключевой механизм метода Дельфи (независимая оценка + управляемое схождение мнений) в уменьшенном для аудитории виде: классический Дельфи предполагает 7 и более анонимных экспертов и нескольких туров через фасилитатора, поэтому версия с двумя экспертами — учебное упрощение, а не полная реализация метода. Балл риска считается только по угрозам, отмеченным флажком на листе «Бланк_студента». Альтернативные методы: метод Саати (МАИ, попарные сравнения весов категорий угроз) точнее учитывает относительную важность категорий, но требует построения матриц попарных сравнений и проверки индекса согласованности; метод Монте-Карло даёт доверительный интервал ущерба через имитационное моделирование по распределениям вероятностей, но требует статистических данных по каждой угрозе, которых на уровне учебного проекта обычно нет. Для аудиторной работы с двумя экспертами балльный Дельфи-подход остаётся наиболее реализуемым.
A16: Источники
A17: 1. Банк данных угроз безопасности информации ФСТЭК России — https://bdu.fstec.ru/threat
A18: 2. Методика оценки угроз безопасности информации, утв. ФСТЭК России 05.02.2021
... A24: 8. CPTED-практика оценки защищённости частных объектов

Sheet База_угроз_эталон
A1: Таблица 1
A2: Единая база данных угроз безопасности объекта заказчика (ландшафт угроз ИБ, 2026 г.)
A4: № | B4: Категория | C4: Код | D4: Наименование угрозы | E4: Типовое проявление / описание | F4: Источник | G4: Частный дом | H4: Офис/фирма | I4: Завод/фабрика | J4: Школа | K4: Бюджетная организация (МФЦ) | L4: Профильный тип проекта
A5: 1 | B5: Информационно-технические (кибер) | C5: У-ИБ-01 | D5: Внедрение вредоносного программного обеспечения | E5: Заражение вирусом, червём, трояном через вложение, сайт или съёмный носитель | F5: БДУ ФСТЭК (bdu.fstec.ru) | G5: X | H5: X | I5: X | J5: X | K5: X | L5: Антивирус корпоративного класса / EDR
A6: 2 | B6: Информационно-технические (кибер) | C6: У-ИБ-02 | D6: Атака программы-вымогателя (ransomware) | E6: Шифрование данных объекта с требованием выкупа за расшифровку | F6: БДУ ФСТЭК; отчёт PT Security CODE RED 2026 | G6: X | H6: X | I6: X | J6: X | K6: X | L6: Антивирус корпоративного класса / EDR
A7: 3 | B7: Информационно-технические (кибер) | C7: У-ИБ-03 | D7: Двойное/тройное вымогательство | E7: Шифрование + кража данных + угроза публикации при отказе платить | F7: PT Security CODE RED 2026; УЦСБ SOC 2025/2026 | H7: X | I7: X | K7: X | L7: Резервное копирование и восстановление (Backup/DR)
A8: 4 | B8: Информационно-технические (кибер) | C8: У-ИБ-04 | D8: Фишинговая рассылка | E8: Массовая рассылка писем с целью получить учётные данные или запустить вредоносный файл | F8: БДУ ФСТЭК; УЦСБ SOC 2025/2026 (60% атак с соц. инженерией) | G8: X | H8: X | I8: X | J8: X | K8: X | L8: Программа обучения персонала (security awareness)
A9: 5 | B9: Информационно-технические (кибер) | C9: У-ИБ-05 | D9: Целевой фишинг (spear-phishing) | E9: Персонализированная атака на конкретного сотрудника, инженера, администратора | F9: MITRE ATT&CK (T1566.001) | H9: X | I9: X | J9: X | K9: X | L9: Программа обучения персонала (security awareness)
A10: 6 | B10: Информационно-технические (кибер) | C10: У-ИБ-06 | D10: Несанкционированный доступ через компрометацию пароля | E10: Подбор, перехват или покупка учётных данных на теневых форумах | F10: БДУ ФСТЭК | G10: X | H10: X | I10: X | J10: X | K10: X | L10: IAM / MFA / SSO
A11: 7 | B11: Информационно-технические (кибер) | C11: У-ИБ-07 | D11: Эксплуатация уязвимостей ПО (включая 0-day) | E11: Использование известной или ранее неизвестной уязвимости для получения доступа | F11: БДУ ФСТЭК (78 120 уязвимостей на 10.2025) | H11: X | I11: X | J11: X | K11: X | L11: Аудит / пентест информационной безопасности
A12: 8 | B12: Информационно-технические (кибер) | C12: У-ИБ-08 | D12: DDoS-атака | E12: Массированные ложные запросы, приводящие к отказу сайта/сервиса (простою) | F12: БДУ ФСТЭК | H12: X | I12: X | J12: X | K12: X | L12: Межсетевой экран / NGFW
A13: 9 | B13: Информационно-технические (кибер) | C13: У-ИБ-09 | D13: Атака «человек посередине» (MITM) | E13: Перехват и подмена трафика в незащищённой (в т.ч. домашней) сети | F13: БДУ ФСТЭК | G13: X | H13: X | I13: X | J13: X | K13: X | L13: Криптографическая защита каналов и данных (СКЗИ)
A14: 10 | B14: Информационно-технические (кибер) | C14: У-ИБ-10 | D14: Компрометация контейнеризированных сред | E14: Модификация образов, нарушение изоляции/целостности контейнеров | F14: БДУ ФСТЭК, обновление июнь 2025 | H14: X | I14: X | K14: X | L14: Аудит / пентест информационной безопасности
A15: 11 | B15: Информационно-технические (кибер) | C15: У-ИБ-11 | D15: Угрозы систем искусственного интеллекта | E15: Отравление данных (data poisoning), состязательные атаки, некорректные решения ИИ-модели | F15: БДУ ФСТЭК, раздел «Угрозы систем ИИ» (2025) | H15: X | I15: X | K15: X | L15: Разработка политики и регламентов ИБ
A16: 12 | B16: Информационно-технические (кибер) | C16: У-ИБ-12 | D16: Мошенничество с использованием deepfake | E16: Поддельные голос/видео руководителя, инженера или родственника для выманивания денег/данных | F16: PT Security CODE RED 2026 | G16: X | H16: X | I16: X | J16: X | K16: X | L16: Программа обучения персонала (security awareness)
A17: 13 | B17: Информационно-технические (кибер) | C17: У-ИБ-13 | D17: Утечка конфиденциальной информации по незащищённым каналам | E17: Передача данных через личную почту, мессенджеры, незашифрованные носители | F17: БДУ ФСТЭК | G17: X | H17: X | I17: X | J17: X | K17: X | L17: DLP-система
A18: 14 | B18: Информационно-технические (кибер) | C18: У-ИБ-14 | D18: Компрометация облачной инфраструктуры | E18: Ошибки конфигурации прав доступа, публичные незащищённые хранилища | F18: БДУ ФСТЭК | H18: X | I18: X | J18: X | K18: X | L18: Аудит / пентест информационной безопасности
A19: 15 | B19: Информационно-технические (кибер) | C19: У-ИБ-15 | D19: Несанкционированный доступ к Wi-Fi сети | E19: Подключение к слабо защищённой беспроводной сети объекта | F19: БДУ ФСТЭК | G19: X | H19: X | I19: X | J19: X | K19: X | L19: Межсетевой экран / NGFW
A20: 16 | B20: Информационно-технические (кибер) | C20: У-ИБ-16 | D20: Компрометация IoT/«умных» устройств | E20: Использование камер, датчиков, «умных» замков как точки входа в сеть | F20: БДУ ФСТЭК | G20: X | H20: X | I20: X | J20: X | K20: X | L20: Межсетевой экран / NGFW
A21: 17 | B21: Информационно-технические (кибер) | C21: У-ИБ-17 | D21: Обход DLP через фото экрана или стеганографию | E21: Вынос конфиденциальных данных в обход контроля каналов передачи | F21: Отраслевая практика DLP-разработчиков | H21: X | I21: X | K21: X | L21: DLP-система
A22: 18 | B22: Информационно-технические (кибер) | C22: У-ИБ-18 | D22: Утечка через теневые ИТ и BYOD-устройства | E22: Использование личных устройств и несогласованных сервисов вне периметра контроля | F22: Отраслевая практика | H22: X | I22: X | J22: X | K22: X | L22: DLP-система
A23: 19 | B23: Информационно-технические (кибер) | C23: У-ИБ-19 | D23: Ошибка конфигурации межсетевого экрана | E23: Избыточно открытые порты и правила, допускающие несанкционированный трафик | F23: Отраслевая практика NGFW-интеграторов | H23: X | I23: X | J23: X | K23: X | L23: Межсетевой экран / NGFW
A24: 20 | B24: Информационно-технические (кибер) | C24: У-ИБ-20 | D24: Обход межсетевого экрана через туннелирование | E24: Сокрытие запрещённого трафика внутри разрешённого протокола | F24: MITRE ATT&CK (T1572) | H24: X | I24: X | K24: X | L24: Межсетевой экран / NGFW
A25: 21 | B25: Информационно-технические (кибер) | C25: У-ИБ-21 | D25: Компрометация единой точки входа (SSO) | E25: Единая учётная запись как единая точка отказа для всех связанных систем | F25: Отраслевая практика IAM | H25: X | I25: X | J25: X | K25: X | L25: IAM / MFA / SSO
A26: 22 | B26: Информационно-технические (кибер) | C26: У-ИБ-22 | D26: Фишинг второго фактора аутентификации | E26: Перехват одноразового кода (OTP) через поддельную форму ввода | F26: MITRE ATT&CK (T1621) | H26: X | I26: X | J26: X | K26: X | L26: IAM / MFA / SSO
A27: 23 | B27: Информационно-технические (кибер) | C27: У-ИБ-23 | D27: SIM-swap (замена SIM-карты) | E27: Перевыпуск SIM-карты жертвы для перехвата кодов подтверждения | F27: Отраслевая практика операторов связи | G27: X | H27: X | L27: IAM / MFA / SSO
A28: 24 | B28: Информационно-технические (кибер) | C28: У-ИБ-24 | D28: Alert fatigue в SIEM/SOC | E28: Переизбыток ложных срабатываний, маскирующий реальный инцидент | F28: Gartner, аналитика SOC 2026 | H28: X | I28: X | K28: X | L28: SIEM / SOC-мониторинг
A29: 25 | B29: Информационно-технические (кибер) | C29: У-ИБ-25 | D29: Слепые зоны логирования | E29: Участки инфраструктуры, не охваченные системой мониторинга событий | F29: Отраслевая практика SOC | H29: X | I29: X | K29: X | L29: SIEM / SOC-мониторинг
A30: 26 | B30: Информационно-технические (кибер) | C30: У-ИБ-26 | D30: Атака на резервные копии | E30: Заражение или шифрование архивных копий данных вместе с основной системой | F30: УЦСБ SOC 2025/2026 | H30: X | I30: X | J30: X | K30: X | L30: Резервное копирование и восстановление (Backup/DR)
A31: 27 | B31: Информационно-технические (кибер) | C31: У-ИБ-27 | D31: Неработоспособность резервной копии при восстановлении | E31: Отсутствие проверки целостности и восстанавливаемости бэкапа до инцидента | F31: Отраслевая практика | G31: X | H31: X | I31: X | J31: X | K31: X | L31: Резервное копирование и восстановление (Backup/DR)
A32: 28 | B32: Информационно-технические (кибер) | C32: У-ИБ-28 | D32: Компрометация или утрата ключей шифрования | E32: Потеря контроля над криптографическим ключом, обесценивающая защиту данных | F32: ГОСТ Р ИСО/МЭК 15408-1-2012 (общая модель угроз) | H32: X | I32: X | K32: X | L32: Криптографическая защита каналов и данных (СКЗИ)
A33: 29 | B33: Информационно-технические (кибер) | C33: У-ИБ-29 | D33: Использование устаревших криптоалгоритмов | E33: Применение схем, не отвечающих текущим требованиям стойкости | F33: NIST IR 8547 (график вывода RSA-2048/ECDSA из обращения) | H33: X | I33: X | K33: X | L33: Криптографическая защита каналов и данных (СКЗИ)
A34: 30 | B34: Информационно-технические (кибер) | C34: У-ИБ-30 | D34: «Harvest now, decrypt later» | E34: Перехват и накопление зашифрованных данных сегодня для расшифровки будущим квантовым компьютером | F34: Zscaler, QRAMM — прогноз Q-day 2030-2035 | H34: X | I34: X | K34: X | L34: Криптографическая защита каналов и данных (СКЗИ)
A35: 31 | B35: Цепочка поставок | C35: У-ЦП-01 | D35: Компрометация подрядчика/поставщика услуг | E35: Получение доступа к сети заказчика через взломанного контрагента | F35: УЦСБ SOC 2025/2026 (30% атак 2025 г. через подрядчиков) | G35: X | H35: X | I35: X | J35: X | K35: X | L35: Аудит / пентест информационной безопасности
A36: 32 | B36: Цепочка поставок | C36: У-ЦП-02 | D36: Внедрение вредоносного кода через обновление ПО вендора | E36: Компрометация цепочки поставок программного обеспечения | F36: MITRE ATT&CK (T1195); PT Security CODE RED 2026 | H36: X | I36: X | J36: X | K36: X | L36: Антивирус корпоративного класса / EDR
A37: 33 | B37: Цепочка поставок | C37: У-ЦП-03 | D37: Компрометация учётных записей сервисных инженеров/интеграторов | E37: Использование доступа монтажной/обслуживающей организации во вред заказчику | F37: Отраслевая практика | G37: X | H37: X | I37: X | J37: X | K37: X | L37: IAM / MFA / SSO
A38: 34 | B38: Персонал (инсайдер, человеческий фактор) | C38: У-ПЕРС-01 | D38: Умышленные действия действующего сотрудника | E38: Хищение, порча или передача конкурентам служебной информации | F38: Kaspersky, аналитика инсайдерских угроз | H38: X | I38: X | J38: X | K38: X | L38: DLP-система
A39: 35 | B39: Персонал (инсайдер, человеческий фактор) | C39: У-ПЕРС-02 | D39: Действия бывшего (уволенного) работника | E39: Использование сохранившегося доступа после увольнения | F39: БДУ ФСТЭК; учебник УПЗИ (типология нарушителей) | H39: X | I39: X | J39: X | K39: X | L39: IAM / MFA / SSO
A40: 36 | B40: Персонал (инсайдер, человеческий фактор) | C40: У-ПЕРС-03 | D40: Социальная инженерия | E40: Психологическое манипулирование персоналом для получения доступа или данных | F40: УЦСБ SOC 2025/2026 (60% атак) | G40: X | H40: X | I40: X | J40: X | K40: X | L40: Программа обучения персонала (security awareness)
A41: 37 | B41: Персонал (инсайдер, человеческий фактор) | C41: У-ПЕРС-04 | D41: Ошибка персонала (человеческий фактор) | E41: Непреднамеренное нарушение регламента, забытая постановка на охрану, неверная настройка | F41: Общая практика ИБ | G41: X | H41: X | I41: X | J41: X | K41: X | L41: Программа обучения персонала (security awareness)
A42: 38 | B42: Персонал (инсайдер, человеческий фактор) | C42: У-ПЕРС-05 | D42: Несоблюдение пропускного и внутриобъектового режима | E42: Проход посторонних лиц вследствие нарушения установленных процедур | F42: Постановление Правительства РФ №1006 от 02.08.2019 | H42: X | I42: X | J42: X | K42: X | L42: СКУД (система контроля и управления доступом)
A43: 39 | B43: Персонал (инсайдер, человеческий фактор) | C43: У-ПЕРС-06 | D43: Сговор персонала с внешним нарушителем | E43: Содействие постороннему лицу в получении доступа к активам/помещениям | F43: Учебник УПЗИ (модель нарушителя) | H43: X | I43: X | J43: X | K43: X | L43: Аудит / пентест информационной безопасности
A44: 40 | B44: Физические угрозы имуществу | C44: У-ФИЗ-01 | D44: Кража (хищение) имущества, оборудования, носителей | E44: Хищение материальных ценностей или носителей информации с объекта | F44: Отраслевая практика охранных систем | G44: X | H44: X | I44: X | J44: X | K44: X | L44: СКУД (система контроля и управления доступом)
A45: 41 | B45: Физические угрозы имуществу | C45: У-ФИЗ-02 | D45: Взлом дверей, окон, ограждения периметра | E45: Силовое проникновение через слабо защищённые точки доступа | F45: CPTED-практика (естественный контроль доступа) | G45: X | H45: X | I45: X | J45: X | K45: X | L45: Охранная сигнализация
A46: 42 | B46: Физические угрозы имуществу | C46: У-ФИЗ-03 | D46: Проникновение через технологические/слабозащищённые проёмы | E46: Проход через подвал, вентиляцию, незащищённые технические отверстия | F46: CPTED-практика | G46: X | H46: X | I46: X | J46: X | K46: X | L46: Охранная сигнализация
A47: 43 | B47: Физические угрозы имуществу | C47: У-ФИЗ-04 | D47: Вандализм, умышленная порча имущества | E47: Разрушение или порча оборудования, фасада, ограждения | F47: CPTED-практика | G47: X | H47: X | I47: X | J47: X | K47: X | L47: СОТ (система видеонаблюдения)
A48: 44 | B48: Физические угрозы имуществу | C48: У-ФИЗ-05 | D48: Умышленный поджог | E48: Целенаправленное возгорание с целью причинения ущерба | F48: Общая практика пожарной безопасности | G48: X | H48: X | I48: X | J48: X | K48: X | L48: Пожарная сигнализация
A49: 45 | B49: Физические угрозы имуществу | C49: У-ФИЗ-06 | D49: Повреждение или хищение кабельных линий связи/электропитания | E49: Обрыв, обрезание кабеля сигнализации, связи, электропитания | F49: Отраслевая практика охранных систем | G49: X | H49: X | I49: X | J49: X | K49: X | L49: Комплексный проект ИТСО «под ключ»
A50: 46 | B50: Угрозы жизни, здоровью, террористические | C50: У-ТЕР-01 | D50: Вооружённое нападение на объект | E50: Проникновение вооружённого лица с целью причинения вреда | F50: ФЗ №35-ФЗ «О противодействии терроризму»; Постановление №1006 | G50: X | H50: X | I50: X | J50: X | K50: X | L50: Паспорт безопасности / антитеррористическая защищённость (ПП РФ № 1006)
A51: 47 | B51: Угрозы жизни, здоровью, террористические | C51: У-ТЕР-02 | D51: Угроза размещения взрывного устройства | E51: Закладка или сообщение о закладке взрывного устройства | F51: Постановление Правительства РФ №1006 от 02.08.2019 | H51: X | I51: X | J51: X | K51: X | L51: Паспорт безопасности / антитеррористическая защищённость (ПП РФ № 1006)
A52: 48 | B52: Угрозы жизни, здоровью, террористические | C52: У-ТЕР-03 | D52: Захват заложников | E52: Насильственное удержание людей на объекте | F52: Постановление Правительства РФ №1006 от 02.08.2019 | H52: X | I52: X | J52: X | K52: X | L52: Паспорт безопасности / антитеррористическая защищённость (ПП РФ № 1006)
A53: 49 | B53: Угрозы жизни, здоровью, террористические | C53: У-ТЕР-04 | D53: Пронос токсичных, отравляющих, биологических агентов | E53: Занос опасных веществ на территорию объекта | F53: Постановление Правительства РФ №1006 от 02.08.2019 | I53: X | J53: X | K53: X | L53: Паспорт безопасности / антитеррористическая защищённость (ПП РФ № 1006)
A54: 50 | B54: Угрозы жизни, здоровью, террористические | C54: У-ТЕР-05 | D54: Массовые беспорядки на прилегающей территории | E54: Стихийное скопление людей, создающее угрозу безопасности объекта | F54: ФЗ №35-ФЗ «О противодействии терроризму» | H54: X | I54: X | J54: X | K54: X | L54: СКУД (система контроля и управления доступом)
A55: 51 | B55: Угрозы жизни, здоровью, террористические | C55: У-ТЕР-06 | D55: Заведомо ложное сообщение об акте терроризма | E55: Ложный вызов, влекущий эвакуацию и простой деятельности объекта | F55: Постановление Правительства РФ №1006 от 02.08.2019 | H55: X | I55: X | J55: X | K55: X | L55: Паспорт безопасности / антитеррористическая защищённость (ПП РФ № 1006)
A56: 52 | B56: Природные и техногенные угрозы | C56: У-ПРИР-01 | D56: Пожар вследствие неисправности проводки/оборудования | E56: Возгорание из-за короткого замыкания, перегрузки сети | F56: Общая практика пожарной безопасности (ГОСТ Р 12.х) | G56: X | H56: X | I56: X | J56: X | K56: X | L56: Пожарная сигнализация
A57: 53 | B57: Природные и техногенные угрозы | C57: У-ПРИР-02 | D57: Затопление (протечка, прорыв водопровода/канализации) | E57: Повреждение имущества и оборудования водой | F57: Общая практика | G57: X | H57: X | I57: X | J57: X | K57: X | L57: Комплексный проект ИТСО «под ключ»
A58: 54 | B58: Природные и техногенные угрозы | C58: У-ПРИР-03 | D58: Аварийное отключение электроснабжения | E58: Прекращение работы систем безопасности и информационных систем при отключении питания | F58: Общая практика | G58: X | H58: X | I58: X | J58: X | K58: X | L58: Резервное копирование и восстановление (Backup/DR)
A59: 55 | B59: Природные и техногенные угрозы | C59: У-ПРИР-04 | D59: Стихийное бедствие (ураган, паводок, землетрясение) | E59: Природные явления, повреждающие объект в зависимости от региона расположения | F59: ГОСТ Р 22.0.02 (безопасность в ЧС, термины) | G59: X | H59: X | I59: X | J59: X | K59: X | L59: Комплексный проект ИТСО «под ключ»
A60: 56 | B60: Природные и техногенные угрозы | C60: У-ПРИР-05 | D60: Утечка бытового/технического газа | E60: Разгерметизация газовой линии, создающая угрозу взрыва/отравления | F60: Общая практика | G60: X | H60: X | I60: X | J60: X | K60: X | L60: Пожарная сигнализация
A61: 57 | B61: Природные и техногенные угрозы | C61: У-ПРИР-06 | D61: Обрушение конструктивных элементов здания | E61: Разрушение несущих конструкций вследствие износа, аварии, взрыва | F61: Общая практика | G61: X | H61: X | I61: X | J61: X | K61: X | L61: Комплексный проект ИТСО «под ключ»
A62: 58 | B62: Промышленные системы / КИИ | C62: У-АСУ-01 | D62: Несанкционированное вмешательство в работу ПЛК/SCADA/HMI | E62: Изменение параметров технологического процесса через интерфейс управления | F62: ФЗ №187-ФЗ «О безопасности КИИ»; приказы ФСТЭК №235, №239 | I62: X | L62: Категорирование объекта КИИ (187-ФЗ)
A63: 59 | B63: Промышленные системы / КИИ | C63: У-АСУ-02 | D63: Нарушение технологического процесса вследствие кибератаки на АСУ ТП | E63: Остановка или разбалансировка производственного процесса | F63: Приказ ФСТЭК №239; MITRE ATT&CK for ICS | I63: X | L63: Категорирование объекта КИИ (187-ФЗ)
A64: 60 | B64: Промышленные системы / КИИ | C64: У-АСУ-03 | D64: Физическое повреждение производственного оборудования как способ атаки | E64: Вывод оборудования из строя путём манипуляции режимами работы | F64: Приказ ФСТЭК №239 | I64: X | L64: СОТ (система видеонаблюдения)
A65: 61 | B65: Промышленные системы / КИИ | C65: У-АСУ-04 | D65: Компрометация систем удалённого мониторинга и телеметрии | E65: Несанкционированный доступ к системе диспетчеризации здания/производства (BMS/АСУЗ) | F65: Отраслевая практика; приказ ФСТЭК №239 | I65: X | K65: X | L65: SIEM / SOC-мониторинг
A66: 62 | B66: Организационно-административные | C66: У-ОРГ-01 | D66: Отсутствие или устаревание политики информационной безопасности | E66: Регламенты не пересматривались и не отражают текущую инфраструктуру и угрозы | F66: Учебник УПЗИ; общая практика | H66: X | I66: X | J66: X | K66: X | L66: Разработка политики и регламентов ИБ
A67: 63 | B67: Организационно-административные | C67: У-ОРГ-02 | D67: Формальное выполнение требований без фактического контроля | E67: Документы оформлены, но меры защиты не работают на практике | F67: Общая практика аудита ИБ | H67: X | I67: X | J67: X | K67: X | L67: Аудит / пентест информационной безопасности
A68: 64 | B68: Организационно-административные | C68: У-ОРГ-03 | D68: Несвоевременное категорирование объекта КИИ или его занижение | E68: Объект не отнесён (или намеренно занижен) к нужной категории значимости | F68: ФЗ №187-ФЗ «О безопасности КИИ» | I68: X | L68: Категорирование объекта КИИ (187-ФЗ)
A69: 65 | B69: Организационно-административные | C69: У-ОРГ-04 | D69: Обработка персональных данных без надлежащего правового основания | E69: Нарушение требований 152-ФЗ о согласии субъекта и целях обработки | F69: ФЗ №152-ФЗ «О персональных данных» | G69: X | H69: X | I69: X | J69: X | K69: X | L69: Приведение обработки ПДн в соответствие 152-ФЗ
A70: 66 | B70: Организационно-административные | C70: У-ОРГ-05 | D70: Отсутствие паспорта безопасности объекта или его несоответствие категории | E70: Формальный документ не отражает реальную категорию опасности объекта | F70: Постановление Правительства РФ №1006 от 02.08.2019 | J70: X | K70: X | L70: Паспорт безопасности / антитеррористическая защищённость (ПП РФ № 1006)
A71: 67 | B71: Организационно-административные | C71: У-ОРГ-06 | D71: Отсутствие обучения персонала действиям при угрозах | E71: Персонал не знает алгоритм действий при пожаре, теракте, фишинговой атаке | F71: Постановление Правительства РФ №1006; общая практика | G71: X | H71: X | I71: X | J71: X | K71: X | L71: Программа обучения персонала (security awareness)
A72: 68 | B72: Организационно-административные | C72: У-ОРГ-07 | D72: Формальное («для галочки») прохождение обучения персоналом | E72: Тренинг проведён, но не выработал реальных навыков реагирования | F72: Общая практика security awareness | H72: X | I72: X | J72: X | K72: X | L72: Программа обучения персонала (security awareness)
A73: 69 | B73: Организационно-административные | C73: У-ОРГ-08 | D73: Отсутствие независимого аудита, самооценка выдаётся за проверку | E73: Контроль защищённости проводится теми же, кто её обеспечивает, без независимой стороны | F73: Общая практика аудита ИБ | H73: X | I73: X | J73: X | K73: X | L73: Аудит / пентест информационной безопасности
A74: 70 | B74: Организационно-административные | C74: У-ОРГ-09 | D74: Расхождение фактической конфигурации системы с документацией | E74: Реальные настройки средств защиты не соответствуют описанным в проектной документации | F74: Общая практика аудита ИБ | H74: X | I74: X | J74: X | K74: X | L74: Аудит / пентест информационной безопасности
A76: Как следует из таблицы 1, база расширена с 47 до 70 угроз за счёт включения программно-аппаратных проектов (МЭ/NGFW, DLP, IAM/MFA/SSO, SIEM/SOC, Backup/DR, СКЗИ) и организационно-административных проектов (политика ИБ, категорирование КИИ, 152-ФЗ, паспорт безопасности, аудит, обучение персонала). Колонка «Профильный тип проекта» связывает каждую угрозу с конкретным типом проекта из рулетки на листе «Рулетка_проекта», что позволяет студенту после случайного выбора типа проекта быстро найти относящиеся к нему угрозы и включить их в модель угроз заказчика, дополнив угрозами, актуальными для выбранного ранее объекта защиты.

Sheet Бланк_студента
A1: Модель угроз для объекта заказчика — рабочий бланк студента
A3: Тип объекта → | B3: Частный дом
A4: ФИО студента:
A6: № | B6: Категория | C6: Код | D6: Наименование угрозы | E6: Профильный тип проекта | F6: Флажок студента (v) | G6: Эталон (для проверки) | H6: Проверка
A7: 1 | B7: Информационно-технические (кибер) | C7: У-ИБ-01 | D7: Внедрение вредоносного программного обеспечения | E7: Антивирус корпоративного класса / EDR | G7: =IF(INDEX(База_угроз_эталон!$G$5:$K$5,MATCH($B$3,База_угроз_эталон!$G$4:$K$4,0))="X","X","-") | H7: =IF(TRIM(F7)="","нет отметки",IF((TRIM(F7)="v")=(G7="X"),"верно","неверно"))
A8: 2 | B8: Информационно-технические (кибер) | C8: У-ИБ-02 | D8: Атака программы-вымогателя (ransomware) | E8: Антивирус корпоративного класса / EDR | G8: =IF(INDEX(База_угроз_эталон!$G$6:$K$6,MATCH($B$3,База_угроз_эталон!$G$4:$K$4,0))="X","X","-") | H8: =IF(TRIM(F8)="","нет отметки",IF((TRIM(F8)="v")=(G8="X"),"верно","неверно"))
A9: 3 | B9: Информационно-технические (кибер) | C9: У-ИБ-03 | D9: Двойное/тройное вымогательство | E9: Резервное копирование и восстановление (Backup/DR) | G9: =IF(INDEX(База_угроз_эталон!$G$7:$K$7,MATCH($B$3,База_угроз_эталон!$G$4:$K$4,0))="X","X","-") | H9: =IF(TRIM(F9)="","нет отметки",IF((TRIM(F9)="v")=(G9="X"),"верно","неверно"))
A10: 4 | B10: Информационно-технические (кибер) | C10: У-ИБ-04 | D10: Фишинговая рассылка | E10: Программа обучения персонала (security awareness) | G10: =IF(INDEX(База_угроз_эталон!$G$8:$K$8,MATCH($B$3,База_угроз_эталон!$G$4:$K$4,0))="X","X","-") | H10: =IF(TRIM(F10)="","нет отметки",IF((TRIM(F10)="v")=(G10="X"),"верно","неверно"))
A11: 5 | B11: Информационно-технические (кибер) | C11: У-ИБ-05 | D11: Целевой фишинг (spear-phishing) | E11: Программа обучения персонала (security awareness) | G11: =IF(INDEX(База_угроз_эталон!$G$9:$K$9,MATCH($B$3,База_угроз_эталон!$G$4:$K$4,0))="X","X","-") | H11: =IF(TRIM(F11)="","нет отметки",IF((TRIM(F11)="v")=(G11="X"),"верно","неверно"))
A12: 6 | B12: Информационно-технические (кибер) | C12: У-ИБ-06 | D12: Несанкционированный доступ через компрометацию пароля | E12: IAM / MFA / SSO | G12: =IF(INDEX(База_угроз_эталон!$G$10:$K$10,MATCH($B$3,База_угроз_эталон!$G$4:$K$4,0))="X","X","-") | H12: =IF(TRIM(F12)="","нет отметки",IF((TRIM(F12)="v")=(G12="X"),"верно","неверно"))
A13: 7 | B13: Информационно-технические (кибер) | C13: У-ИБ-07 | D13: Эксплуатация уязвимостей ПО (включая 0-day) | E13: Аудит / пентест информационной безопасности | G13: =IF(INDEX(База_угроз_эталон!$G$11:$K$11,MATCH($B$3,База_угроз_эталон!$G$4:$K$4,0))="X","X","-") | H13: =IF(TRIM(F13)="","нет отметки",IF((TRIM(F13)="v")=(G13="X"),"верно","неверно"))
A14: 8 | B14: Информационно-технические (кибер) | C14: У-ИБ-08 | D14: DDoS-атака | E14: Межсетевой экран / NGFW | G14: =IF(INDEX(База_угроз_эталон!$G$12:$K$12,MATCH($B$3,База_угроз_эталон!$G$4:$K$4,0))="X","X","-") | H14: =IF(TRIM(F14)="","нет отметки",IF((TRIM(F14)="v")=(G14="X"),"верно","неверно"))
A15: 9 | B15: Информационно-технические (кибер) | C15: У-ИБ-09 | D15: Атака «человек посередине» (MITM) | E15: Криптографическая защита каналов и данных (СКЗИ) | G15: =IF(INDEX(База_угроз_эталон!$G$13:$K$13,MATCH($B$3,База_угроз_эталон!$G$4:$K$4,0))="X","X","-") | H15: =IF(TRIM(F15)="","нет отметки",IF((TRIM(F15)="v")=(G15="X"),"верно","неверно"))
A16: 10 | B16: Информационно-технические (кибер) | C16: У-ИБ-10 | D16: Компрометация контейнеризированных сред | E16: Аудит / пентест информационной безопасности | G16: =IF(INDEX(База_угроз_эталон!$G$14:$K$14,MATCH($B$3,База_угроз_эталон!$G$4:$K$4,0))="X","X","-") | H16: =IF(TRIM(F16)="","нет отметки",IF((TRIM(F16)="v")=(G16="X"),"верно","неверно"))
A17: 11 | B17: Информационно-технические (кибер) | C17: У-ИБ-11 | D17: Угрозы систем искусственного интеллекта | E17: Разработка политики и регламентов ИБ | G17: =IF(INDEX(База_угроз_эталон!$G$15:$K$15,MATCH($B$3,База_угроз_эталон!$G$4:$K$4,0))="X","X","-") | H17: =IF(TRIM(F17)="","нет отметки",IF((TRIM(F17)="v")=(G17="X"),"верно","неверно"))
A18: 12 | B18: Информационно-технические (кибер) | C18: У-ИБ-12 | D18: Мошенничество с использованием deepfake | E18: Программа обучения персонала (security awareness) | G18: =IF(INDEX(База_угроз_эталон!$G$16:$K$16,MATCH($B$3,База_угроз_эталон!$G$4:$K$4,0))="X","X","-") | H18: =IF(TRIM(F18)="","нет отметки",IF((TRIM(F18)="v")=(G18="X"),"верно","неверно"))
A19: 13 | B19: Информационно-технические (кибер) | C19: У-ИБ-13 | D19: Утечка конфиденциальной информации по незащищённым каналам | E19: DLP-система | G19: =IF(INDEX(База_угроз_эталон!$G$17:$K$17,MATCH($B$3,База_угроз_эталон!$G$4:$K$4,0))="X","X","-") | H19: =IF(TRIM(F19)="","нет отметки",IF((TRIM(F19)="v")=(G19="X"),"верно","неверно"))
A20: 14 | B20: Информационно-технические (кибер) | C20: У-ИБ-14 | D20: Компрометация облачной инфраструктуры | E20: Аудит / пентест информационной безопасности | G20: =IF(INDEX(База_угроз_эталон!$G$18:$K$18,MATCH($B$3,База_угроз_эталон!$G$4:$K$4,0))="X","X","-") | H20: =IF(TRIM(F20)="","нет отметки",IF((TRIM(F20)="v")=(G20="X"),"верно","неверно"))
A21: 15 | B21: Информационно-технические (кибер) | C21: У-ИБ-15 | D21: Несанкционированный доступ к Wi-Fi сети | E21: Межсетевой экран / NGFW | G21: =IF(INDEX(База_угроз_эталон!$G$19:$K$19,MATCH($B$3,База_угроз_эталон!$G$4:$K$4,0))="X","X","-") | H21: =IF(TRIM(F21)="","нет отметки",IF((TRIM(F21)="v")=(G21="X"),"верно","неверно"))
A22: 16 | B22: Информационно-технические (кибер) | C22: У-ИБ-16 | D22: Компрометация IoT/«умных» устройств | E22: Межсетевой экран / NGFW | G22: =IF(INDEX(База_угроз_эталон!$G$20:$K$20,MATCH($B$3,База_угроз_эталон!$G$4:$K$4,0))="X","X","-") | H22: =IF(TRIM(F22)="","нет отметки",IF((TRIM(F22)="v")=(G22="X"),"верно","неверно"))
A23: 17 | B23: Информационно-технические (кибер) | C23: У-ИБ-17 | D23: Обход DLP через фото экрана или стеганографию | E23: DLP-система | G23: =IF(INDEX(База_угроз_эталон!$G$21:$K$21,MATCH($B$3,База_угроз_эталон!$G$4:$K$4,0))="X","X","-") | H23: =IF(TRIM(F23)="","нет отметки",IF((TRIM(F23)="v")=(G23="X"),"верно","неверно"))
A24: 18 | B24: Информационно-технические (кибер) | C24: У-ИБ-18 | D24: Утечка через теневые ИТ и BYOD-устройства | E24: DLP-система | G24: =IF(INDEX(База_угроз_эталон!$G$22:$K$22,MATCH($B$3,База_угроз_эталон!$G$4:$K$4,0))="X","X","-") | H24: =IF(TRIM(F24)="","нет отметки",IF((TRIM(F24)="v")=(G24="X"),"верно","неверно"))
A25: 19 | B25: Информационно-технические (кибер) | C25: У-ИБ-19 | D25: Ошибка конфигурации межсетевого экрана | E25: Межсетевой экран / NGFW | G25: =IF(INDEX(База_угроз_эталон!$G$23:$K$23,MATCH($B$3,База_угроз_эталон!$G$4:$K$4,0))="X","X","-") | H25: =IF(TRIM(F25)="","нет отметки",IF((TRIM(F25)="v")=(G25="X"),"верно","неверно"))
A26: 20 | B26: Информационно-технические (кибер) | C26: У-ИБ-20 | D26: Обход межсетевого экрана через туннелирование | E26: Межсетевой экран / NGFW | G26: =IF(INDEX(База_угроз_эталон!$G$24:$K$24,MATCH($B$3,База_угроз_эталон!$G$4:$K$4,0))="X","X","-") | H26: =IF(TRIM(F26)="","нет отметки",IF((TRIM(F26)="v")=(G26="X"),"верно","неверно"))
A27: 21 | B27: Информационно-технические (кибер) | C27: У-ИБ-21 | D27: Компрометация единой точки входа (SSO) | E27: IAM / MFA / SSO | G27: =IF(INDEX(База_угроз_эталон!$G$25:$K$25,MATCH($B$3,База_угроз_эталон!$G$4:$K$4,0))="X","X","-") | H27: =IF(TRIM(F27)="","нет отметки",IF((TRIM(F27)="v")=(G27="X"),"верно","неверно"))
A28: 22 | B28: Информационно-технические (кибер) | C28: У-ИБ-22 | D28: Фишинг второго фактора аутентификации | E28: IAM / MFA / SSO | G28: =IF(INDEX(База_угроз_эталон!$G$26:$K$26,MATCH($B$3,База_угроз_эталон!$G$4:$K$4,0))="X","X","-") | H28: =IF(TRIM(F28)="","нет отметки",IF((TRIM(F28)="v")=(G28="X"),"верно","неверно"))
A29: 23 | B29: Информационно-технические (кибер) | C29: У-ИБ-23 | D29: SIM-swap (замена SIM-карты) | E29: IAM / MFA / SSO | G29: =IF(INDEX(База_угроз_эталон!$G$27:$K$27,MATCH($B$3,База_угроз_эталон!$G$4:$K$4,0))="X","X","-") | H29: =IF(TRIM(F29)="","нет отметки",IF((TRIM(F29)="v")=(G29="X"),"верно","неверно"))
A30: 24 | B30: Информационно-технические (кибер) | C30: У-ИБ-24 | D30: Alert fatigue в SIEM/SOC | E30: SIEM / SOC-мониторинг | G30: =IF(INDEX(База_угроз_эталон!$G$28:$K$28,MATCH($B$3,База_угроз_эталон!$G$4:$K$4,0))="X","X","-") | H30: =IF(TRIM(F30)="","нет отметки",IF((TRIM(F30)="v")=(G30="X"),"верно","неверно"))
A31: 25 | B31: Информационно-технические (кибер) | C31: У-ИБ-25 | D31: Слепые зоны логирования | E31: SIEM / SOC-мониторинг | G31: =IF(INDEX(База_угроз_эталон!$G$29:$K$29,MATCH($B$3,База_угроз_эталон!$G$4:$K$4,0))="X","X","-") | H31: =IF(TRIM(F31)="","нет отметки",IF((TRIM(F31)="v")=(G31="X"),"верно","неверно"))
A32: 26 | B32: Информационно-технические (кибер) | C32: У-ИБ-26 | D32: Атака на резервные копии | E32: Резервное копирование и восстановление (Backup/DR) | G32: =IF(INDEX(База_угроз_эталон!$G$30:$K$30,MATCH($B$3,База_угроз_эталон!$G$4:$K$4,0))="X","X","-") | H32: =IF(TRIM(F32)="","нет отметки",IF((TRIM(F32)="v")=(G32="X"),"верно","неверно"))
A33: 27 | B33: Информационно-технические (кибер) | C33: У-ИБ-27 | D33: Неработоспособность резервной копии при восстановлении | E33: Резервное копирование и восстановление (Backup/DR) | G33: =IF(INDEX(База_угроз_эталон!$G$31:$K$31,MATCH($B$3,База_угроз_эталон!$G$4:$K$4,0))="X","X","-") | H33: =IF(TRIM(F33)="","нет отметки",IF((TRIM(F33)="v")=(G33="X"),"верно","неверно"))
A34: 28 | B34: Информационно-технические (кибер) | C34: У-ИБ-28 | D34: Компрометация или утрата ключей шифрования | E34: Криптографическая защита каналов и данных (СКЗИ) | G34: =IF(INDEX(База_угроз_эталон!$G$32:$K$32,MATCH($B$3,База_угроз_эталон!$G$4:$K$4,0))="X","X","-") | H34: =IF(TRIM(F34)="","нет отметки",IF((TRIM(F34)="v")=(G34="X"),"верно","неверно"))
A35: 29 | B35: Информационно-технические (кибер) | C35: У-ИБ-29 | D35: Использование устаревших криптоалгоритмов | E35: Криптографическая защита каналов и данных (СКЗИ) | G35: =IF(INDEX(База_угроз_эталон!$G$33:$K$33,MATCH($B$3,База_угроз_эталон!$G$4:$K$4,0))="X","X","-") | H35: =IF(TRIM(F35)="","нет отметки",IF((TRIM(F35)="v")=(G35="X"),"верно","неверно"))
A36: 30 | B36: Информационно-технические (кибер) | C36: У-ИБ-30 | D36: «Harvest now, decrypt later» | E36: Криптографическая защита каналов и данных (СКЗИ) | G36: =IF(INDEX(База_угроз_эталон!$G$34:$K$34,MATCH($B$3,База_угроз_эталон!$G$4:$K$4,0))="X","X","-") | H36: =IF(TRIM(F36)="","нет отметки",IF((TRIM(F36)="v")=(G36="X"),"верно","неверно"))
A37: 31 | B37: Цепочка поставок | C37: У-ЦП-01 | D37: Компрометация подрядчика/поставщика услуг | E37: Аудит / пентест информационной безопасности | G37: =IF(INDEX(База_угроз_эталон!$G$35:$K$35,MATCH($B$3,База_угроз_эталон!$G$4:$K$4,0))="X","X","-") | H37: =IF(TRIM(F37)="","нет отметки",IF((TRIM(F37)="v")=(G37="X"),"верно","неверно"))
A38: 32 | B38: Цепочка поставок | C38: У-ЦП-02 | D38: Внедрение вредоносного кода через обновление ПО вендора | E38: Антивирус корпоративного класса / EDR | G38: =IF(INDEX(База_угроз_эталон!$G$36:$K$36,MATCH($B$3,База_угроз_эталон!$G$4:$K$4,0))="X","X","-") | H38: =IF(TRIM(F38)="","нет отметки",IF((TRIM(F38)="v")=(G38="X"),"верно","неверно"))
A39: 33 | B39: Цепочка поставок | C39: У-ЦП-03 | D39: Компрометация учётных записей сервисных инженеров/интеграторов | E39: IAM / MFA / SSO | G39: =IF(INDEX(База_угроз_эталон!$G$37:$K$37,MATCH($B$3,База_угроз_эталон!$G$4:$K$4,0))="X","X","-") | H39: =IF(TRIM(F39)="","нет отметки",IF((TRIM(F39)="v")=(G39="X"),"верно","неверно"))
A40: 34 | B40: Персонал (инсайдер, человеческий фактор) | C40: У-ПЕРС-01 | D40: Умышленные действия действующего сотрудника | E40: DLP-система | G40: =IF(INDEX(База_угроз_эталон!$G$38:$K$38,MATCH($B$3,База_угроз_эталон!$G$4:$K$4,0))="X","X","-") | H40: =IF(TRIM(F40)="","нет отметки",IF((TRIM(F40)="v")=(G40="X"),"верно","неверно"))
A41: 35 | B41: Персонал (инсайдер, человеческий фактор) | C41: У-ПЕРС-02 | D41: Действия бывшего (уволенного) работника | E41: IAM / MFA / SSO | G41: =IF(INDEX(База_угроз_эталон!$G$39:$K$39,MATCH($B$3,База_угроз_эталон!$G$4:$K$4,0))="X","X","-") | H41: =IF(TRIM(F41)="","нет отметки",IF((TRIM(F41)="v")=(G41="X"),"верно","неверно"))
A42: 36 | B42: Персонал (инсайдер, человеческий фактор) | C42: У-ПЕРС-03 | D42: Социальная инженерия | E42: Программа обучения персонала (security awareness) | G42: =IF(INDEX(База_угроз_эталон!$G$40:$K$40,MATCH($B$3,База_угроз_эталон!$G$4:$K$4,0))="X","X","-") | H42: =IF(TRIM(F42)="","нет отметки",IF((TRIM(F42)="v")=(G42="X"),"верно","неверно"))
A43: 37 | B43: Персонал (инсайдер, человеческий фактор) | C43: У-ПЕРС-04 | D43: Ошибка персонала (человеческий фактор) | E43: Программа обучения персонала (security awareness) | G43: =IF(INDEX(База_угроз_эталон!$G$41:$K$41,MATCH($B$3,База_угроз_эталон!$G$4:$K$4,0))="X","X","-") | H43: =IF(TRIM(F43)="","нет отметки",IF((TRIM(F43)="v")=(G43="X"),"верно","неверно"))
A44: 38 | B44: Персонал (инсайдер, человеческий фактор) | C44: У-ПЕРС-05 | D44: Несоблюдение пропускного и внутриобъектового режима | E44: СКУД (система контроля и управления доступом) | G44: =IF(INDEX(База_угроз_эталон!$G$42:$K$42,MATCH($B$3,База_угроз_эталон!$G$4:$K$4,0))="X","X","-") | H44: =IF(TRIM(F44)="","нет отметки",IF((TRIM(F44)="v")=(G44="X"),"верно","неверно"))
A45: 39 | B45: Персонал (инсайдер, человеческий фактор) | C45: У-ПЕРС-06 | D45: Сговор персонала с внешним нарушителем | E45: Аудит / пентест информационной безопасности | G45: =IF(INDEX(База_угроз_эталон!$G$43:$K$43,MATCH($B$3,База_угроз_эталон!$G$4:$K$4,0))="X","X","-") | H45: =IF(TRIM(F45)="","нет отметки",IF((TRIM(F45)="v")=(G45="X"),"верно","неверно"))
A46: 40 | B46: Физические угрозы имуществу | C46: У-ФИЗ-01 | D46: Кража (хищение) имущества, оборудования, носителей | E46: СКУД (система контроля и управления доступом) | G46: =IF(INDEX(База_угроз_эталон!$G$44:$K$44,MATCH($B$3,База_угроз_эталон!$G$4:$K$4,0))="X","X","-") | H46: =IF(TRIM(F46)="","нет отметки",IF((TRIM(F46)="v")=(G46="X"),"верно","неверно"))
A47: 41 | B47: Физические угрозы имуществу | C47: У-ФИЗ-02 | D47: Взлом дверей, окон, ограждения периметра | E47: Охранная сигнализация | G47: =IF(INDEX(База_угроз_эталон!$G$45:$K$45,MATCH($B$3,База_угроз_эталон!$G$4:$K$4,0))="X","X","-") | H47: =IF(TRIM(F47)="","нет отметки",IF((TRIM(F47)="v")=(G47="X"),"верно","неверно"))
A48: 42 | B48: Физические угрозы имуществу | C48: У-ФИЗ-03 | D48: Проникновение через технологические/слабозащищённые проёмы | E48: Охранная сигнализация | G48: =IF(INDEX(База_угроз_эталон!$G$46:$K$46,MATCH($B$3,База_угроз_эталон!$G$4:$K$4,0))="X","X","-") | H48: =IF(TRIM(F48)="","нет отметки",IF((TRIM(F48)="v")=(G48="X"),"верно","неверно"))
A49: 43 | B49: Физические угрозы имуществу | C49: У-ФИЗ-04 | D49: Вандализм, умышленная порча имущества | E49: СОТ (система видеонаблюдения) | G49: =IF(INDEX(База_угроз_эталон!$G$47:$K$47,MATCH($B$3,База_угроз_эталон!$G$4:$K$4,0))="X","X","-") | H49: =IF(TRIM(F49)="","нет отметки",IF((TRIM(F49)="v")=(G49="X"),"верно","неверно"))
A50: 44 | B50: Физические угрозы имуществу | C50: У-ФИЗ-05 | D50: Умышленный поджог | E50: Пожарная сигнализация | G50: =IF(INDEX(База_угроз_эталон!$G$48:$K$48,MATCH($B$3,База_угроз_эталон!$G$4:$K$4,0))="X","X","-") | H50: =IF(TRIM(F50)="","нет отметки",IF((TRIM(F50)="v")=(G50="X"),"верно","неверно"))
A51: 45 | B51: Физические угрозы имуществу | C51: У-ФИЗ-06 | D51: Повреждение или хищение кабельных линий связи/электропитания | E51: Комплексный проект ИТСО «под ключ» | G51: =IF(INDEX(База_угроз_эталон!$G$49:$K$49,MATCH($B$3,База_угроз_эталон!$G$4:$K$4,0))="X","X","-") | H51: =IF(TRIM(F51)="","нет отметки",IF((TRIM(F51)="v")=(G51="X"),"верно","неверно"))
A52: 46 | B52: Угрозы жизни, здоровью, террористические | C52: У-ТЕР-01 | D52: Вооружённое нападение на объект | E52: Паспорт безопасности / антитеррористическая защищённость (ПП РФ № 1006) | G52: =IF(INDEX(База_угроз_эталон!$G$50:$K$50,MATCH($B$3,База_угроз_эталон!$G$4:$K$4,0))="X","X","-") | H52: =IF(TRIM(F52)="","нет отметки",IF((TRIM(F52)="v")=(G52="X"),"верно","неверно"))
A53: 47 | B53: Угрозы жизни, здоровью, террористические | C53: У-ТЕР-02 | D53: Угроза размещения взрывного устройства | E53: Паспорт безопасности / антитеррористическая защищённость (ПП РФ № 1006) | G53: =IF(INDEX(База_угроз_эталон!$G$51:$K$51,MATCH($B$3,База_угроз_эталон!$G$4:$K$4,0))="X","X","-") | H53: =IF(TRIM(F53)="","нет отметки",IF((TRIM(F53)="v")=(G53="X"),"верно","неверно"))
A54: 48 | B54: Угрозы жизни, здоровью, террористические | C54: У-ТЕР-03 | D54: Захват заложников | E54: Паспорт безопасности / антитеррористическая защищённость (ПП РФ № 1006) | G54: =IF(INDEX(База_угроз_эталон!$G$52:$K$52,MATCH($B$3,База_угроз_эталон!$G$4:$K$4,0))="X","X","-") | H54: =IF(TRIM(F54)="","нет отметки",IF((TRIM(F54)="v")=(G54="X"),"верно","неверно"))
A55: 49 | B55: Угрозы жизни, здоровью, террористические | C55: У-ТЕР-04 | D55: Пронос токсичных, отравляющих, биологических агентов | E55: Паспорт безопасности / антитеррористическая защищённость (ПП РФ № 1006) | G55: =IF(INDEX(База_угроз_эталон!$G$53:$K$53,MATCH($B$3,База_угроз_эталон!$G$4:$K$4,0))="X","X","-") | H55: =IF(TRIM(F55)="","нет отметки",IF((TRIM(F55)="v")=(G55="X"),"верно","неверно"))
A56: 50 | B56: Угрозы жизни, здоровью, террористические | C56: У-ТЕР-05 | D56: Массовые беспорядки на прилегающей территории | E56: СКУД (система контроля и управления доступом) | G56: =IF(INDEX(База_угроз_эталон!$G$54:$K$54,MATCH($B$3,База_угроз_эталон!$G$4:$K$4,0))="X","X","-") | H56: =IF(TRIM(F56)="","нет отметки",IF((TRIM(F56)="v")=(G56="X"),"верно","неверно"))
A57: 51 | B57: Угрозы жизни, здоровью, террористические | C57: У-ТЕР-06 | D57: Заведомо ложное сообщение об акте терроризма | E57: Паспорт безопасности / антитеррористическая защищённость (ПП РФ № 1006) | G57: =IF(INDEX(База_угроз_эталон!$G$55:$K$55,MATCH($B$3,База_угроз_эталон!$G$4:$K$4,0))="X","X","-") | H57: =IF(TRIM(F57)="","нет отметки",IF((TRIM(F57)="v")=(G57="X"),"верно","неверно"))
A58: 52 | B58: Природные и техногенные угрозы | C58: У-ПРИР-01 | D58: Пожар вследствие неисправности проводки/оборудования | E58: Пожарная сигнализация | G58: =IF(INDEX(База_угроз_эталон!$G$56:$K$56,MATCH($B$3,База_угроз_эталон!$G$4:$K$4,0))="X","X","-") | H58: =IF(TRIM(F58)="","нет отметки",IF((TRIM(F58)="v")=(G58="X"),"верно","неверно"))
A59: 53 | B59: Природные и техногенные угрозы | C59: У-ПРИР-02 | D59: Затопление (протечка, прорыв водопровода/канализации) | E59: Комплексный проект ИТСО «под ключ» | G59: =IF(INDEX(База_угроз_эталон!$G$57:$K$57,MATCH($B$3,База_угроз_эталон!$G$4:$K$4,0))="X","X","-") | H59: =IF(TRIM(F59)="","нет отметки",IF((TRIM(F59)="v")=(G59="X"),"верно","неверно"))
A60: 54 | B60: Природные и техногенные угрозы | C60: У-ПРИР-03 | D60: Аварийное отключение электроснабжения | E60: Резервное копирование и восстановление (Backup/DR) | G60: =IF(INDEX(База_угроз_эталон!$G$58:$K$58,MATCH($B$3,База_угроз_эталон!$G$4:$K$4,0))="X","X","-") | H60: =IF(TRIM(F60)="","нет отметки",IF((TRIM(F60)="v")=(G60="X"),"верно","неверно"))
A61: 55 | B61: Природные и техногенные угрозы | C61: У-ПРИР-04 | D61: Стихийное бедствие (ураган, паводок, землетрясение) | E61: Комплексный проект ИТСО «под ключ» | G61: =IF(INDEX(База_угроз_эталон!$G$59:$K$59,MATCH($B$3,База_угроз_эталон!$G$4:$K$4,0))="X","X","-") | H61: =IF(TRIM(F61)="","нет отметки",IF((TRIM(F61)="v")=(G61="X"),"верно","неверно"))
A62: 56 | B62: Природные и техногенные угрозы | C62: У-ПРИР-05 | D62: Утечка бытового/технического газа | E62: Пожарная сигнализация | G62: =IF(INDEX(База_угроз_эталон!$G$60:$K$60,MATCH($B$3,База_угроз_эталон!$G$4:$K$4,0))="X","X","-") | H62: =IF(TRIM(F62)="","нет отметки",IF((TRIM(F62)="v")=(G62="X"),"верно","неверно"))
A63: 57 | B63: Природные и техногенные угрозы | C63: У-ПРИР-06 | D63: Обрушение конструктивных элементов здания | E63: Комплексный проект ИТСО «под ключ» | G63: =IF(INDEX(База_угроз_эталон!$G$61:$K$61,MATCH($B$3,База_угроз_эталон!$G$4:$K$4,0))="X","X","-") | H63: =IF(TRIM(F63)="","нет отметки",IF((TRIM(F63)="v")=(G63="X"),"верно","неверно"))
A64: 58 | B64: Промышленные системы / КИИ | C64: У-АСУ-01 | D64: Несанкционированное вмешательство в работу ПЛК/SCADA/HMI | E64: Категорирование объекта КИИ (187-ФЗ) | G64: =IF(INDEX(База_угроз_эталон!$G$62:$K$62,MATCH($B$3,База_угроз_эталон!$G$4:$K$4,0))="X","X","-") | H64: =IF(TRIM(F64)="","нет отметки",IF((TRIM(F64)="v")=(G64="X"),"верно","неверно"))
A65: 59 | B65: Промышленные системы / КИИ | C65: У-АСУ-02 | D65: Нарушение технологического процесса вследствие кибератаки на АСУ ТП | E65: Категорирование объекта КИИ (187-ФЗ) | G65: =IF(INDEX(База_угроз_эталон!$G$63:$K$63,MATCH($B$3,База_угроз_эталон!$G$4:$K$4,0))="X","X","-") | H65: =IF(TRIM(F65)="","нет отметки",IF((TRIM(F65)="v")=(G65="X"),"верно","неверно"))
A66: 60 | B66: Промышленные системы / КИИ | C66: У-АСУ-03 | D66: Физическое повреждение производственного оборудования как способ атаки | E66: СОТ (система видеонаблюдения) | G66: =IF(INDEX(База_угроз_эталон!$G$64:$K$64,MATCH($B$3,База_угроз_эталон!$G$4:$K$4,0))="X","X","-") | H66: =IF(TRIM(F66)="","нет отметки",IF((TRIM(F66)="v")=(G66="X"),"верно","неверно"))
A67: 61 | B67: Промышленные системы / КИИ | C67: У-АСУ-04 | D67: Компрометация систем удалённого мониторинга и телеметрии | E67: SIEM / SOC-мониторинг | G67: =IF(INDEX(База_угроз_эталон!$G$65:$K$65,MATCH($B$3,База_угроз_эталон!$G$4:$K$4,0))="X","X","-") | H67: =IF(TRIM(F67)="","нет отметки",IF((TRIM(F67)="v")=(G67="X"),"верно","неверно"))
A68: 62 | B68: Организационно-административные | C68: У-ОРГ-01 | D68: Отсутствие или устаревание политики информационной безопасности | E68: Разработка политики и регламентов ИБ | G68: =IF(INDEX(База_угроз_эталон!$G$66:$K$66,MATCH($B$3,База_угроз_эталон!$G$4:$K$4,0))="X","X","-") | H68: =IF(TRIM(F68)="","нет отметки",IF((TRIM(F68)="v")=(G68="X"),"верно","неверно"))
A69: 63 | B69: Организационно-административные | C69: У-ОРГ-02 | D69: Формальное выполнение требований без фактического контроля | E69: Аудит / пентест информационной безопасности | G69: =IF(INDEX(База_угроз_эталон!$G$67:$K$67,MATCH($B$3,База_угроз_эталон!$G$4:$K$4,0))="X","X","-") | H69: =IF(TRIM(F69)="","нет отметки",IF((TRIM(F69)="v")=(G69="X"),"верно","неверно"))
A70: 64 | B70: Организационно-административные | C70: У-ОРГ-03 | D70: Несвоевременное категорирование объекта КИИ или его занижение | E70: Категорирование объекта КИИ (187-ФЗ) | G70: =IF(INDEX(База_угроз_эталон!$G$68:$K$68,MATCH($B$3,База_угроз_эталон!$G$4:$K$4,0))="X","X","-") | H70: =IF(TRIM(F70)="","нет отметки",IF((TRIM(F70)="v")=(G70="X"),"верно","неверно"))
A71: 65 | B71: Организационно-административные | C71: У-ОРГ-04 | D71: Обработка персональных данных без надлежащего правового основания | E71: Приведение обработки ПДн в соответствие 152-ФЗ | G71: =IF(INDEX(База_угроз_эталон!$G$69:$K$69,MATCH($B$3,База_угроз_эталон!$G$4:$K$4,0))="X","X","-") | H71: =IF(TRIM(F71)="","нет отметки",IF((TRIM(F71)="v")=(G71="X"),"верно","неверно"))
A72: 66 | B72: Организационно-административные | C72: У-ОРГ-05 | D72: Отсутствие паспорта безопасности объекта или его несоответствие категории | E72: Паспорт безопасности / антитеррористическая защищённость (ПП РФ № 1006) | G72: =IF(INDEX(База_угроз_эталон!$G$70:$K$70,MATCH($B$3,База_угроз_эталон!$G$4:$K$4,0))="X","X","-") | H72: =IF(TRIM(F72)="","нет отметки",IF((TRIM(F72)="v")=(G72="X"),"верно","неверно"))
A73: 67 | B73: Организационно-административные | C73: У-ОРГ-06 | D73: Отсутствие обучения персонала действиям при угрозах | E73: Программа обучения персонала (security awareness) | G73: =IF(INDEX(База_угроз_эталон!$G$71:$K$71,MATCH($B$3,База_угроз_эталон!$G$4:$K$4,0))="X","X","-") | H73: =IF(TRIM(F73)="","нет отметки",IF((TRIM(F73)="v")=(G73="X"),"верно","неверно"))
A74: 68 | B74: Организационно-административные | C74: У-ОРГ-07 | D74: Формальное («для галочки») прохождение обучения персоналом | E74: Программа обучения персонала (security awareness) | G74: =IF(INDEX(База_угроз_эталон!$G$72:$K$72,MATCH($B$3,База_угроз_эталон!$G$4:$K$4,0))="X","X","-") | H74: =IF(TRIM(F74)="","нет отметки",IF((TRIM(F74)="v")=(G74="X"),"верно","неверно"))
A75: 69 | B75: Организационно-административные | C75: У-ОРГ-08 | D75: Отсутствие независимого аудита, самооценка выдаётся за проверку | E75: Аудит / пентест информационной безопасности | G75: =IF(INDEX(База_угроз_эталон!$G$73:$K$73,MATCH($B$3,База_угроз_эталон!$G$4:$K$4,0))="X","X","-") | H75: =IF(TRIM(F75)="","нет отметки",IF((TRIM(F75)="v")=(G75="X"),"верно","неверно"))
A76: 70 | B76: Организационно-административные | C76: У-ОРГ-09 | D76: Расхождение фактической конфигурации системы с документацией | E76: Аудит / пентест информационной безопасности | G76: =IF(INDEX(База_угроз_эталон!$G$74:$K$74,MATCH($B$3,База_угроз_эталон!$G$4:$K$4,0))="X","X","-") | H76: =IF(TRIM(F76)="","нет отметки",IF((TRIM(F76)="v")=(G76="X"),"верно","неверно"))
D78: Верных совпадений с эталоном: | G78: =COUNTIF(H7:H76,"верно")&" из "&70

Sheet Рулетка_проекта
A1: Рулетка «Тип проекта ИБ» — три сундука, 20 типов проектов
H2: Полный список (для формулы, не удалять):
A3: Сундук I — ИТСО | C3: Сундук II — программно-аппаратный проект | E3: Сундук III — организационно-административный проект | H3: СКУД (система контроля и управления доступом)
A4: СКУД (система контроля и управления доступом) | C4: Межсетевой экран / NGFW | E4: Разработка политики и регламентов ИБ | H4: СОТ (система видеонаблюдения)
A5: СОТ (система видеонаблюдения) | C5: DLP-система | E5: Категорирование объекта КИИ (187-ФЗ) | H5: Охранная сигнализация
A6: Охранная сигнализация | C6: IAM / MFA / SSO | E6: Приведение обработки ПДн в соответствие 152-ФЗ | H6: Пожарная сигнализация
A7: Пожарная сигнализация | C7: SIEM / SOC-мониторинг | E7: Паспорт безопасности / антитеррористическая защищённость (ПП РФ № 1006) | H7: Периметральное ограждение и турникеты
A8: Периметральное ограждение и турникеты | C8: Антивирус корпоративного класса / EDR | E8: Аудит / пентест информационной безопасности | H8: Комплексный проект ИТСО «под ключ»
A9: Комплексный проект ИТСО «под ключ» | C9: VPN для защищённого удалённого доступа | E9: Программа обучения персонала (security awareness) | H9: Межсетевой экран / NGFW
C10: Резервное копирование и восстановление (Backup/DR) | H10: DLP-система
C11: Криптографическая защита каналов и данных (СКЗИ) | H11: IAM / MFA / SSO
A12: Результат рулетки: | B12: =INDEX($H$3:$H$22,RANDBETWEEN(1,20)) | H12: SIEM / SOC-мониторинг
A13: Как «крутить»: кликните в жёлтую ячейку «Крутить» ниже, введите любое число и нажмите Enter — рулетка пересчитается сама (F9 не нужен; на Mac F9 занят яркостью экрана). | H13: Антивирус корпоративного класса / EDR
A14: Крутить (введите число и нажмите Enter): | H14: VPN для защищённого удалённого доступа
A15: Объект защиты (с листа «Бланк_студента»): | C15: =Бланк_студента!B3 | H15: Резервное копирование и восстановление (Backup/DR)
H16: Криптографическая защита каналов и данных (СКЗИ)
A17: Логически сочетаются? (впишите сами: да / нет) | H17: Разработка политики и регламентов ИБ
H18: Категорирование объекта КИИ (187-ФЗ)
A19: Обоснование (если «нет» — почему проект неприменим к объекту и какая замена была бы разумнее): | H19: Приведение обработки ПДн в соответствие 152-ФЗ
H20: Паспорт безопасности / антитеррористическая защищённость (ПП РФ № 1006)
H21: Аудит / пентест информационной безопасности
H22: Программа обучения персонала (security awareness)
A26: Угрозы, профильные для выпавшего проекта (см. столбец «Профильный тип проекта» на листе «База_угроз_эталон» / «Бланк_студента»), нужно включить в модель угроз заказчика в дополнение к угрозам, актуальным для выбранного объекта защиты.

Sheet Оценка_риска_Дельфи
A1: Балльная оценка риска объекта ДО внедрения проекта ИБ (мини-метод Дельфи, 2 эксперта)
A2: Метод: Риск = Вероятность (P) x Тяжесть ущерба (I), где P и I оцениваются по шкале 1-5 двумя экспертами (студент и приглашённый одногруппник) независимо друг от друга - раунд 1. Если оценки расходятся на 2 балла и более, столбец «Нужен раунд 2?» показывает «обсудите»: эксперты обсуждают расхождение и вписывают согласованные P и I вручную поверх формулы-подсказки (среднего значения). Балл риска считается только по угрозам, отмеченным флажком на листе «Бланк_студента». Это учебная мини-версия метода Дельфи (классический вариант предполагает 7+ анонимных экспертов и несколько туров через фасилитатора); методы Саати (МАИ) и Монте-Карло точнее, но существенно сложнее для ручной аудиторной работы - см. пояснение на листе «Инструкция».
A6: Эксперт 1 (ФИО): | D6: Эксперт 2 (ФИО одногруппника):
A7: Объект защиты (с листа «Бланк_студента»): | D7: =Бланк_студента!B3
A9: № | B9: Код | C9: Наименование угрозы | D9: Отмечена студентом? | E9: Эксперт 1: P (1-5) | F9: Эксперт 1: I (1-5) | G9: Эксперт 2: P (1-5) | H9: Эксперт 2: I (1-5) | I9: delta P | J9: delta I | K9: Нужен раунд 2? | L9: Согласованная P | M9: Согласованная I | N9: Балл риска (P x I)
A10: 1 | B10: У-ИБ-01 | C10: Внедрение вредоносного программного обеспечения | D10: =IF(Бланк_студента!F7="","",Бланк_студента!F7) | I10: =IF(AND(ISNUMBER(E10),ISNUMBER(G10)),ABS(E10-G10),"") | J10: =IF(AND(ISNUMBER(F10),ISNUMBER(H10)),ABS(F10-H10),"") | K10: =IF(OR(AND(ISNUMBER(I10),I10>=2),AND(ISNUMBER(J10),J10>=2)),"обсудите (раунд 2)",IF(AND(ISNUMBER(I10),ISNUMBER(J10)),"согласовано","")) | L10: =IFERROR(AVERAGE(E10,G10),"") | M10: =IFERROR(AVERAGE(F10,H10),"") | N10: =IF(AND(ISNUMBER(L10),ISNUMBER(M10)),L10*M10,0)
A11: 2 | B11: У-ИБ-02 | C11: Атака программы-вымогателя (ransomware) | D11: =IF(Бланк_студента!F8="","",Бланк_студента!F8) | I11: =IF(AND(ISNUMBER(E11),ISNUMBER(G11)),ABS(E11-G11),"") | J11: =IF(AND(ISNUMBER(F11),ISNUMBER(H11)),ABS(F11-H11),"") | K11: =IF(OR(AND(ISNUMBER(I11),I11>=2),AND(ISNUMBER(J11),J11>=2)),"обсудите (раунд 2)",IF(AND(ISNUMBER(I11),ISNUMBER(J11)),"согласовано","")) | L11: =IFERROR(AVERAGE(E11,G11),"") | M11: =IFERROR(AVERAGE(F11,H11),"") | N11: =IF(AND(ISNUMBER(L11),ISNUMBER(M11)),L11*M11,0)
A12: 3 | B12: У-ИБ-03 | C12: Двойное/тройное вымогательство | D12: =IF(Бланк_студента!F9="","",Бланк_студента!F9) | I12: =IF(AND(ISNUMBER(E12),ISNUMBER(G12)),ABS(E12-G12),"") | J12: =IF(AND(ISNUMBER(F12),ISNUMBER(H12)),ABS(F12-H12),"") | K12: =IF(OR(AND(ISNUMBER(I12),I12>=2),AND(ISNUMBER(J12),J12>=2)),"обсудите (раунд 2)",IF(AND(ISNUMBER(I12),ISNUMBER(J12)),"согласовано","")) | L12: =IFERROR(AVERAGE(E12,G12),"") | M12: =IFERROR(AVERAGE(F12,H12),"") | N12: =IF(AND(ISNUMBER(L12),ISNUMBER(M12)),L12*M12,0)
A13: 4 | B13: У-ИБ-04 | C13: Фишинговая рассылка | D13: =IF(Бланк_студента!F10="","",Бланк_студента!F10) | I13: =IF(AND(ISNUMBER(E13),ISNUMBER(G13)),ABS(E13-G13),"") | J13: =IF(AND(ISNUMBER(F13),ISNUMBER(H13)),ABS(F13-H13),"") | K13: =IF(OR(AND(ISNUMBER(I13),I13>=2),AND(ISNUMBER(J13),J13>=2)),"обсудите (раунд 2)",IF(AND(ISNUMBER(I13),ISNUMBER(J13)),"согласовано","")) | L13: =IFERROR(AVERAGE(E13,G13),"") | M13: =IFERROR(AVERAGE(F13,H13),"") | N13: =IF(AND(ISNUMBER(L13),ISNUMBER(M13)),L13*M13,0)
A14: 5 | B14: У-ИБ-05 | C14: Целевой фишинг (spear-phishing) | D14: =IF(Бланк_студента!F11="","",Бланк_студента!F11) | I14: =IF(AND(ISNUMBER(E14),ISNUMBER(G14)),ABS(E14-G14),"") | J14: =IF(AND(ISNUMBER(F14),ISNUMBER(H14)),ABS(F14-H14),"") | K14: =IF(OR(AND(ISNUMBER(I14),I14>=2),AND(ISNUMBER(J14),J14>=2)),"обсудите (раунд 2)",IF(AND(ISNUMBER(I14),ISNUMBER(J14)),"согласовано","")) | L14: =IFERROR(AVERAGE(E14,G14),"") | M14: =IFERROR(AVERAGE(F14,H14),"") | N14: =IF(AND(ISNUMBER(L14),ISNUMBER(M14)),L14*M14,0)
A15: 6 | B15: У-ИБ-06 | C15: Несанкционированный доступ через компрометацию пароля | D15: =IF(Бланк_студента!F12="","",Бланк_студента!F12) | I15: =IF(AND(ISNUMBER(E15),ISNUMBER(G15)),ABS(E15-G15),"") | J15: =IF(AND(ISNUMBER(F15),ISNUMBER(H15)),ABS(F15-H15),"") | K15: =IF(OR(AND(ISNUMBER(I15),I15>=2),AND(ISNUMBER(J15),J15>=2)),"обсудите (раунд 2)",IF(AND(ISNUMBER(I15),ISNUMBER(J15)),"согласовано","")) | L15: =IFERROR(AVERAGE(E15,G15),"") | M15: =IFERROR(AVERAGE(F15,H15),"") | N15: =IF(AND(ISNUMBER(L15),ISNUMBER(M15)),L15*M15,0)
A16: 7 | B16: У-ИБ-07 | C16: Эксплуатация уязвимостей ПО (включая 0-day) | D16: =IF(Бланк_студента!F13="","",Бланк_студента!F13) | I16: =IF(AND(ISNUMBER(E16),ISNUMBER(G16)),ABS(E16-G16),"") | J16: =IF(AND(ISNUMBER(F16),ISNUMBER(H16)),ABS(F16-H16),"") | K16: =IF(OR(AND(ISNUMBER(I16),I16>=2),AND(ISNUMBER(J16),J16>=2)),"обсудите (раунд 2)",IF(AND(ISNUMBER(I16),ISNUMBER(J16)),"согласовано","")) | L16: =IFERROR(AVERAGE(E16,G16),"") | M16: =IFERROR(AVERAGE(F16,H16),"") | N16: =IF(AND(ISNUMBER(L16),ISNUMBER(M16)),L16*M16,0)
A17: 8 | B17: У-ИБ-08 | C17: DDoS-атака | D17: =IF(Бланк_студента!F14="","",Бланк_студента!F14) | I17: =IF(AND(ISNUMBER(E17),ISNUMBER(G17)),ABS(E17-G17),"") | J17: =IF(AND(ISNUMBER(F17),ISNUMBER(H17)),ABS(F17-H17),"") | K17: =IF(OR(AND(ISNUMBER(I17),I17>=2),AND(ISNUMBER(J17),J17>=2)),"обсудите (раунд 2)",IF(AND(ISNUMBER(I17),ISNUMBER(J17)),"согласовано","")) | L17: =IFERROR(AVERAGE(E17,G17),"") | M17: =IFERROR(AVERAGE(F17,H17),"") | N17: =IF(AND(ISNUMBER(L17),ISNUMBER(M17)),L17*M17,0)
A18: 9 | B18: У-ИБ-09 | C18: Атака «человек посередине» (MITM) | D18: =IF(Бланк_студента!F15="","",Бланк_студента!F15) | I18: =IF(AND(ISNUMBER(E18),ISNUMBER(G18)),ABS(E18-G18),"") | J18: =IF(AND(ISNUMBER(F18),ISNUMBER(H18)),ABS(F18-H18),"") | K18: =IF(OR(AND(ISNUMBER(I18),I18>=2),AND(ISNUMBER(J18),J18>=2)),"обсудите (раунд 2)",IF(AND(ISNUMBER(I18),ISNUMBER(J18)),"согласовано","")) | L18: =IFERROR(AVERAGE(E18,G18),"") | M18: =IFERROR(AVERAGE(F18,H18),"") | N18: =IF(AND(ISNUMBER(L18),ISNUMBER(M18)),L18*M18,0)
A19: 10 | B19: У-ИБ-10 | C19: Компрометация контейнеризированных сред | D19: =IF(Бланк_студента!F16="","",Бланк_студента!F16) | I19: =IF(AND(ISNUMBER(E19),ISNUMBER(G19)),ABS(E19-G19),"") | J19: =IF(AND(ISNUMBER(F19),ISNUMBER(H19)),ABS(F19-H19),"") | K19: =IF(OR(AND(ISNUMBER(I19),I19>=2),AND(ISNUMBER(J19),J19>=2)),"обсудите (раунд 2)",IF(AND(ISNUMBER(I19),ISNUMBER(J19)),"согласовано","")) | L19: =IFERROR(AVERAGE(E19,G19),"") | M19: =IFERROR(AVERAGE(F19,H19),"") | N19: =IF(AND(ISNUMBER(L19),ISNUMBER(M19)),L19*M19,0)
A20: 11 | B20: У-ИБ-11 | C20: Угрозы систем искусственного интеллекта | D20: =IF(Бланк_студента!F17="","",Бланк_студента!F17) | I20: =IF(AND(ISNUMBER(E20),ISNUMBER(G20)),ABS(E20-G20),"") | J20: =IF(AND(ISNUMBER(F20),ISNUMBER(H20)),ABS(F20-H20),"") | K20: =IF(OR(AND(ISNUMBER(I20),I20>=2),AND(ISNUMBER(J20),J20>=2)),"обсудите (раунд 2)",IF(AND(ISNUMBER(I20),ISNUMBER(J20)),"согласовано","")) | L20: =IFERROR(AVERAGE(E20,G20),"") | M20: =IFERROR(AVERAGE(F20,H20),"") | N20: =IF(AND(ISNUMBER(L20),ISNUMBER(M20)),L20*M20,0)
A21: 12 | B21: У-ИБ-12 | C21: Мошенничество с использованием deepfake | D21: =IF(Бланк_студента!F18="","",Бланк_студента!F18) | I21: =IF(AND(ISNUMBER(E21),ISNUMBER(G21)),ABS(E21-G21),"") | J21: =IF(AND(ISNUMBER(F21),ISNUMBER(H21)),ABS(F21-H21),"") | K21: =IF(OR(AND(ISNUMBER(I21),I21>=2),AND(ISNUMBER(J21),J21>=2)),"обсудите (раунд 2)",IF(AND(ISNUMBER(I21),ISNUMBER(J21)),"согласовано","")) | L21: =IFERROR(AVERAGE(E21,G21),"") | M21: =IFERROR(AVERAGE(F21,H21),"") | N21: =IF(AND(ISNUMBER(L21),ISNUMBER(M21)),L21*M21,0)
... A79: 70 | B79: У-ОРГ-09 | C79: Расхождение фактической конфигурации системы с документацией | D79: =IF(Бланк_студента!F76="","",Бланк_студента!F76) | I79: =IF(AND(ISNUMBER(E79),ISNUMBER(G79)),ABS(E79-G79),"") | J79: =IF(AND(ISNUMBER(F79),ISNUMBER(H79)),ABS(F79-H79),"") | K79: =IF(OR(AND(ISNUMBER(I79),I79>=2),AND(ISNUMBER(J79),J79>=2)),"обсудите (раунд 2)",IF(AND(ISNUMBER(I79),ISNUMBER(J79)),"согласовано","")) | L79: =IFERROR(AVERAGE(E79,G79),"") | M79: =IFERROR(AVERAGE(F79,H79),"") | N79: =IF(AND(ISNUMBER(L79),ISNUMBER(M79)),L79*M79,0)
C81: Количество отмеченных угроз: | F81: =COUNTIF(D10:D79,"v")
C82: Суммарный балл риска (по отмеченным угрозам): | F82: =SUMPRODUCT((D10:D79="v")*N10:N79)
C83: Средний балл риска на угрозу: | F83: =IFERROR(F82/F81,0)
C84: Индекс риска объекта ДО проекта (0-100%): | F84: =TEXT(F83/25*100,"0.0")&"%"
A86: Полученный индекс риска - это показатель «ДО» (аналог входного аудита ИБ в примере ПАО «Ростелеком» и показателя бюджетозащищённости МФЦ из приложенных материалов курса). После того как на листе «Рулетка_проекта» определён тип проекта ИБ и он спроектирован (веха 2), нужно скопировать этот лист, переоценить P (как правило, именно вероятность снижается после внедрения контрмер) и получить показатель «ПОСЛЕ» - снижение суммарного балла риска станет технико-экономическим обоснованием выбранного проекта, по той же логике, что и рост доходозащищённости/бюджетозащищённости в исходных методических материалах.
