Workbook

Sheet Ставки_персонала_01
A1: ЭТАЛОН — БЛОК 01: СТАВКИ ПЕРСОНАЛА ФИРМЫ-ИСПОЛНИТЕЛЯ
A2: Используется для расчёта трудозатрат в Смете (блок 04) и Бюджете (блок 05). Синим — вводимые ставки (можно скорректировать под свой регион).
A4: Роль | B4: Ставка, ₽/час | C4: Ставка, ₽/день (=час×8) | D4: Портфель, где преимущественно занят | E4: Источник / примечание
A5: Руководитель проекта | B5: 950 | C5: =B5*8 -> 7600 | D5: I / II / III | E5: оценка на основе вилки руководителей ИБ-проектов интеграторов, 2026
A6: Инженер проекта | B6: 830 | C6: =B6*8 -> 6640 | D6: I | E6: ГородРабот.ру: инженер по видеонаблюдению, средняя ЗП ~140000 ₽/мес ÷ 168 ч ≈ 833 ₽/час, 2026
A7: Проектировщик | B7: 750 | C7: =B7*8 -> 6000 | D7: I | E7: оценка по аналогии со ставкой инженера проекта, ниже на разряд
A8: Монтажник | B8: 550 | C8: =B8*8 -> 4400 | D8: I | E8: hh.ru/ГородРабот.ру: монтажник систем безопасности 76200-111800 ₽/мес (РФ/Москва) ÷ 168 ч ≈ 454-665 ₽/час, среднее, 2026
A9: Мастер (бригадир монтажа) | B9: 700 | C9: =B9*8 -> 5600 | D9: I | E9: оценка: монтажник + надбавка за руководство бригадой
A10: Зав. складом | B10: 450 | C10: =B10*8 -> 3600 | D10: I | E10: оценка по типовой ставке складского персонала интегратора
A11: Юрист-договорник | B11: 900 | C11: =B11*8 -> 7200 | D11: I / II / III | E11: оценка по рыночной ставке юриста на аутсорсе для сопровождения договоров подряда
A12: Инженер-интегратор ПО/ИБ | B12: 1100 | C12: =B12*8 -> 8800 | D12: II | E12: оценка на основе вилки инженеров SIEM/NGFW-интеграторов, вакансии 2026
A13: ИБ-аналитик / аудитор | B13: 1300 | C13: =B13*8 -> 10400 | D13: III | E13: оценка на основе вилки консультантов по аудиту ИБ (Информзащита, Positive Technologies), 2026
A14: Специалист по обучению персонала | B14: 700 | C14: =B14*8 -> 5600 | D14: III | E14: оценка по рыночной ставке тренера по security awareness

Sheet Смета_20типов_04
A1: ЭТАЛОН — БЛОК 04: СМЕТА ПРОЕКТА ИБ (20 ТИПОВ)
A2: Формула: Стоимость труда (трудозатраты × 8ч × ставка) + Материалы (Middle, из «Комплектующие_20типов») + Накладные % = Смета. Синим — вводимые значения. Трудозатраты портфеля I — суммы применимых задач листа «Гантт_ИТСО (6 типов)»; трудозатраты портфелей II и III — суммы применимых задач листа «Гантт_Софт_Орг (14 типов)» (исправлено: ранее стояли приближённые экспертные оценки без ссылки на фактические данные Ганта).
A4: Средняя ставка портфеля, ₽/час (ссылка на лист «Ставки_персонала_01»):
A5: Портфель I (ИТСО, монтаж) = | B5: =AVERAGE(Ставки_персонала_01!B6:B10) -> 656
A6: Портфель II (программно-аппаратный) = | B6: =Ставки_персонала_01!B12 -> 1100
A7: Портфель III (организационно-административный) = | B7: =AVERAGE(Ставки_персонала_01!B13:B14) -> 1000
A9: № | B9: Код | C9: Тип проекта | D9: Портфель | E9: Трудозатраты, чел-дни | F9: Ставка портфеля, ₽/час | G9: Стоимость труда, ₽ (=E×8×F) | H9: Материалы (Middle), ₽ источник: Комплектующие_20типов | I9: Накладные, % | J9: Накладные, ₽ (=(G+H)×I) | K9: ИТОГО СМЕТА, ₽ (=G+H+J)
A10: 1 | B10: skud | C10: СКУД (система контроля и управления доступом) | D10: I | E10: 66.5 | F10: =B5 -> 656 | G10: =E10*8*F10 -> 348992 | H10: 142000 | I10: 0.15 | J10: =(G10+H10)*I10 -> 73648.8 | K10: =G10+H10+J10 -> 564640.8
A11: 2 | B11: video | C11: СОТ (система видеонаблюдения) | D11: I | E11: 65 | F11: =B5 -> 656 | G11: =E11*8*F11 -> 341120 | H11: 66090 | I11: 0.15 | J11: =(G11+H11)*I11 -> 61081.5 | K11: =G11+H11+J11 -> 468291.5
A12: 3 | B12: fire | C12: Пожарная сигнализация | D12: I | E12: 66.5 | F12: =B5 -> 656 | G12: =E12*8*F12 -> 348992 | H12: 57900 | I12: 0.15 | J12: =(G12+H12)*I12 -> 61033.8 | K12: =G12+H12+J12 -> 467925.8
A13: 4 | B13: security | C13: Охранная сигнализация | D13: I | E13: 66.5 | F13: =B5 -> 656 | G13: =E13*8*F13 -> 348992 | H13: 13553 | I13: 0.15 | J13: =(G13+H13)*I13 -> 54381.75 | K13: =G13+H13+J13 -> 416926.75
A14: 5 | B14: perimeter | C14: Периметральное ограждение и турникеты | D14: I | E14: 70 | F14: =B5 -> 656 | G14: =E14*8*F14 -> 367360 | H14: 70000 | I14: 0.15 | J14: =(G14+H14)*I14 -> 65604 | K14: =G14+H14+J14 -> 502964
A15: 6 | B15: hybrid | C15: Комплексный проект ИТСО «под ключ» | D15: I | E15: 76 | F15: =B5 -> 656 | G15: =E15*8*F15 -> 398848 | H15: 240000 | I15: 0.15 | J15: =(G15+H15)*I15 -> 95827.2 | K15: =G15+H15+J15 -> 734675.2
A16: 7 | B16: ngfw | C16: Межсетевой экран / NGFW | D16: II | E16: 55 | F16: =B6 -> 1100 | G16: =E16*8*F16 -> 484000 | H16: 700000 | I16: 0.15 | J16: =(G16+H16)*I16 -> 177600 | K16: =G16+H16+J16 -> 1361600
A17: 8 | B17: dlp | C17: DLP-система | D17: II | E17: 52 | F17: =B6 -> 1100 | G17: =E17*8*F17 -> 457600 | H17: 900000 | I17: 0.15 | J17: =(G17+H17)*I17 -> 203640 | K17: =G17+H17+J17 -> 1561240
A18: 9 | B18: iam | C18: IAM / MFA / SSO | D18: II | E18: 55 | F18: =B6 -> 1100 | G18: =E18*8*F18 -> 484000 | H18: 1200000 | I18: 0.15 | J18: =(G18+H18)*I18 -> 252600 | K18: =G18+H18+J18 -> 1936600
A19: 10 | B19: siem | C19: SIEM / SOC-мониторинг | D19: II | E19: 51 | F19: =B6 -> 1100 | G19: =E19*8*F19 -> 448800 | H19: 1500000 | I19: 0.15 | J19: =(G19+H19)*I19 -> 292320 | K19: =G19+H19+J19 -> 2241120
A20: 11 | B20: edr | C20: Антивирус корпоративного класса / EDR | D20: II | E20: 48 | F20: =B6 -> 1100 | G20: =E20*8*F20 -> 422400 | H20: 600000 | I20: 0.15 | J20: =(G20+H20)*I20 -> 153360 | K20: =G20+H20+J20 -> 1175760
A21: 12 | B21: vpn | C21: VPN для защищённого удалённого доступа | D21: II | E21: 52 | F21: =B6 -> 1100 | G21: =E21*8*F21 -> 457600 | H21: 450000 | I21: 0.15 | J21: =(G21+H21)*I21 -> 136140 | K21: =G21+H21+J21 -> 1043740
A22: 13 | B22: backup | C22: Резервное копирование и восстановление (Backup/DR) | D22: II | E22: 42 | F22: =B6 -> 1100 | G22: =E22*8*F22 -> 369600 | H22: 250000 | I22: 0.15 | J22: =(G22+H22)*I22 -> 92940 | K22: =G22+H22+J22 -> 712540
A23: 14 | B23: crypto | C23: Криптографическая защита каналов и данных (СКЗИ) | D23: II | E23: 44 | F23: =B6 -> 1100 | G23: =E23*8*F23 -> 387200 | H23: 70000 | I23: 0.15 | J23: =(G23+H23)*I23 -> 68580 | K23: =G23+H23+J23 -> 525780
A24: 15 | B24: policy | C24: Разработка политики и регламентов ИБ | D24: III | E24: 28 | F24: =B7 -> 1000 | G24: =E24*8*F24 -> 224000 | H24: 250000 | I24: 0.15 | J24: =(G24+H24)*I24 -> 71100 | K24: =G24+H24+J24 -> 545100
A25: 16 | B25: kii | C25: Категорирование объекта КИИ (187-ФЗ) | D25: III | E25: 34 | F25: =B7 -> 1000 | G25: =E25*8*F25 -> 272000 | H25: 400000 | I25: 0.15 | J25: =(G25+H25)*I25 -> 100800 | K25: =G25+H25+J25 -> 772800
A26: 17 | B26: pdn | C26: Приведение обработки ПДн в соответствие 152-ФЗ | D26: III | E26: 34 | F26: =B7 -> 1000 | G26: =E26*8*F26 -> 272000 | H26: 200000 | I26: 0.15 | J26: =(G26+H26)*I26 -> 70800 | K26: =G26+H26+J26 -> 542800
A27: 18 | B27: passport | C27: Паспорт безопасности / антитеррористическая защищённость | D27: III | E27: 15 | F27: =B7 -> 1000 | G27: =E27*8*F27 -> 120000 | H27: 60000 | I27: 0.15 | J27: =(G27+H27)*I27 -> 27000 | K27: =G27+H27+J27 -> 207000
A28: 19 | B28: audit | C28: Аудит / пентест информационной безопасности | D28: III | E28: 34 | F28: =B7 -> 1000 | G28: =E28*8*F28 -> 272000 | H28: 500000 | I28: 0.15 | J28: =(G28+H28)*I28 -> 115800 | K28: =G28+H28+J28 -> 887800
A29: 20 | B29: training | C29: Программа обучения персонала (security awareness) | D29: III | E29: 18 | F29: =B7 -> 1000 | G29: =E29*8*F29 -> 144000 | H29: 5000 | I29: 0.15 | J29: =(G29+H29)*I29 -> 22350 | K29: =G29+H29+J29 -> 171350
F30: Итого по 20 типам: | G30: =SUM(G10:G29) -> 6969504 | H30: =SUM(H10:H29) -> 7674543 | J30: =SUM(J10:J29) -> 2196607 | K30: =SUM(K10:K29) -> 16840654
A32: Примечание: трудозатраты по портфелю I взяты из суммы длительностей этапов листа «Гантт_ИТСО (6 типов)» (Спр_обучение_v1.xlsx); по портфелям II и III — экспертная оценка на основе типовых сроков внедрения аналогичных систем ИБ (2026). Накладные расходы 15% — типовая ставка по методике МДС 81-35.2004 (прямые затраты + накладные + плановая прибыль); преподаватель может скорректировать процент под конкретную фирму.

Sheet Бюджет_20типов_05
A1: ЭТАЛОН — БЛОК 05: БЮДЖЕТ ПРОЕКТА ИБ (time-фазированное распределение Сметы)
A2: Смета (блок 04) распределяется во времени по трём траншам согласно этапам приёмки Договора. Проценты — вводимые (синим), можно менять под конкретный договор.
A4: Доли траншей:
A5: Аванс при подписании Договора | B5: 0.3
A6: Промежуточный транш (по акту выполнения этапа монтажа/настройки) | B6: 0.4
A7: Окончательный расчёт (по акту КС-2/КС-3, сдача проекта) | B7: 0.3
A8: Контроль суммы долей (должно быть 100%): | B8: =B5+B6+B7 -> 1
A10: № | B10: Код | C10: Тип проекта | D10: Смета (Итого), ₽ [ссылка на лист «Смета_20типов_04»] | E10: Аванс, ₽ | F10: Промежуточный, ₽ | G10: Окончательный, ₽ | H10: Проверка (=E+F+G, должно = D)
A11: 1 | B11: skud | C11: СКУД (система контроля и управления доступом) | D11: =Смета_20типов_04!K10 -> 564640.8 | E11: =$D11*$B$5 -> 169392.24 | F11: =$D11*$B$6 -> 225856.32 | G11: =$D11*$B$7 -> 169392.24 | H11: =E11+F11+G11-D11 -> 0
A12: 2 | B12: video | C12: СОТ (система видеонаблюдения) | D12: =Смета_20типов_04!K11 -> 468291.5 | E12: =$D12*$B$5 -> 140487.45 | F12: =$D12*$B$6 -> 187316.6 | G12: =$D12*$B$7 -> 140487.45 | H12: =E12+F12+G12-D12 -> 0
A13: 3 | B13: fire | C13: Пожарная сигнализация | D13: =Смета_20типов_04!K12 -> 467925.8 | E13: =$D13*$B$5 -> 140377.74 | F13: =$D13*$B$6 -> 187170.32 | G13: =$D13*$B$7 -> 140377.74 | H13: =E13+F13+G13-D13 -> 0
A14: 4 | B14: security | C14: Охранная сигнализация | D14: =Смета_20типов_04!K13 -> 416926.75 | E14: =$D14*$B$5 -> 125078.02 | F14: =$D14*$B$6 -> 166770.7 | G14: =$D14*$B$7 -> 125078.02 | H14: =E14+F14+G14-D14 -> 0
A15: 5 | B15: perimeter | C15: Периметральное ограждение и турникеты | D15: =Смета_20типов_04!K14 -> 502964 | E15: =$D15*$B$5 -> 150889.2 | F15: =$D15*$B$6 -> 201185.6 | G15: =$D15*$B$7 -> 150889.2 | H15: =E15+F15+G15-D15 -> 0
A16: 6 | B16: hybrid | C16: Комплексный проект ИТСО «под ключ» | D16: =Смета_20типов_04!K15 -> 734675.2 | E16: =$D16*$B$5 -> 220402.56 | F16: =$D16*$B$6 -> 293870.08 | G16: =$D16*$B$7 -> 220402.56 | H16: =E16+F16+G16-D16 -> 0
A17: 7 | B17: ngfw | C17: Межсетевой экран / NGFW | D17: =Смета_20типов_04!K16 -> 1361600 | E17: =$D17*$B$5 -> 408480 | F17: =$D17*$B$6 -> 544640 | G17: =$D17*$B$7 -> 408480 | H17: =E17+F17+G17-D17 -> 0
A18: 8 | B18: dlp | C18: DLP-система | D18: =Смета_20типов_04!K17 -> 1561240 | E18: =$D18*$B$5 -> 468372 | F18: =$D18*$B$6 -> 624496 | G18: =$D18*$B$7 -> 468372 | H18: =E18+F18+G18-D18 -> 0
A19: 9 | B19: iam | C19: IAM / MFA / SSO | D19: =Смета_20типов_04!K18 -> 1936600 | E19: =$D19*$B$5 -> 580980 | F19: =$D19*$B$6 -> 774640 | G19: =$D19*$B$7 -> 580980 | H19: =E19+F19+G19-D19 -> 0
A20: 10 | B20: siem | C20: SIEM / SOC-мониторинг | D20: =Смета_20типов_04!K19 -> 2241120 | E20: =$D20*$B$5 -> 672336 | F20: =$D20*$B$6 -> 896448 | G20: =$D20*$B$7 -> 672336 | H20: =E20+F20+G20-D20 -> 0
A21: 11 | B21: edr | C21: Антивирус корпоративного класса / EDR | D21: =Смета_20типов_04!K20 -> 1175760 | E21: =$D21*$B$5 -> 352728 | F21: =$D21*$B$6 -> 470304 | G21: =$D21*$B$7 -> 352728 | H21: =E21+F21+G21-D21 -> 0
A22: 12 | B22: vpn | C22: VPN для защищённого удалённого доступа | D22: =Смета_20типов_04!K21 -> 1043740 | E22: =$D22*$B$5 -> 313122 | F22: =$D22*$B$6 -> 417496 | G22: =$D22*$B$7 -> 313122 | H22: =E22+F22+G22-D22 -> 0
... A30: 20 | B30: training | C30: Программа обучения персонала (security awareness) | D30: =Смета_20типов_04!K29 -> 171350 | E30: =$D30*$B$5 -> 51405 | F30: =$D30*$B$6 -> 68540 | G30: =$D30*$B$7 -> 51405 | H30: =E30+F30+G30-D30 -> 0
C31: ИТОГО: | D31: =SUM(D11:D30) -> 16840654 | E31: =SUM(E11:E30) -> 5052196.2 | F31: =SUM(F11:F30) -> 6736261.6 | G31: =SUM(G11:G30) -> 5052196.2
A33: Примечание: колонка «Проверка» должна давать 0 (или близко к 0 из-за округления) — если нет, доли траншей в B5:B7 не суммируются в 100% и требуют исправления. Расхождение между плановым Бюджетом и фактической потребностью в деньгах на конкретном этапе — это и есть «дефицит», разбираемый в блоке 07 диаграммы «Концепция...» части 2.
